LICENSE
MANIFEST.in
README.rst
requirements.txt
setup.py
lib/pcapyplus/__init__.py
lib/pcapyplus/bpfobj.cpp
lib/pcapyplus/dumper.cpp
lib/pcapyplus/pcapyplus.cpp
lib/pcapyplus/pkthdr.cpp
lib/pcapyplus/reader.cpp
lib/pcapyplus.egg-info/PKG-INFO
lib/pcapyplus.egg-info/SOURCES.txt
lib/pcapyplus.egg-info/dependency_links.txt
lib/pcapyplus.egg-info/not-zip-safe
lib/pcapyplus.egg-info/top_level.txt
lib/pcapyplus/include/bpfobj.hpp
lib/pcapyplus/include/dumper.hpp
lib/pcapyplus/include/pcapyplus.hpp
lib/pcapyplus/include/pkthdr.hpp
lib/pcapyplus/include/reader.hpp
test/test_pcapyplus.py