Metadata-Version: 2.1
Name: pcapyplus
Version: 1.0.0
Summary: Python extension module to access libpcap
Home-page: https://github.com/HPENetworking/pcapyplus
Author: Hewlett Packard Enterprise Development LP
Author-email: sdk_tools_frameworks@groups.ext.hpe.com
License: UNKNOWN
Keywords: pcapyplus
Platform: UNKNOWN
Classifier: Development Status :: 5 - Production/Stable
Classifier: Intended Audience :: Developers
Classifier: License :: OSI Approved :: Apache Software License
Classifier: Natural Language :: English
Classifier: Operating System :: POSIX :: Linux
Classifier: Programming Language :: Python :: 3
Classifier: Programming Language :: Python :: 3.8
Requires-Python: >=3.8
License-File: LICENSE
